pytestee/__init__.py
pytestee/main.py
pytestee/py.typed
pytestee/registry.py
pytestee/adapters/__init__.py
pytestee/adapters/cli/__init__.py
pytestee/adapters/cli/commands.py
pytestee/adapters/cli/handlers/__init__.py
pytestee/adapters/cli/handlers/achievement_rate_handler.py
pytestee/adapters/cli/handlers/base_handler.py
pytestee/adapters/cli/handlers/check_handler.py
pytestee/adapters/cli/handlers/info_handler.py
pytestee/adapters/cli/handlers/list_checkers_handler.py
pytestee/adapters/cli/handlers/show_config_handler.py
pytestee/adapters/cli/services/__init__.py
pytestee/adapters/cli/services/output_service.py
pytestee/adapters/presenters/__init__.py
pytestee/adapters/presenters/achievement_rate_presenter.py
pytestee/adapters/presenters/console_presenter.py
pytestee/adapters/repositories/__init__.py
pytestee/adapters/repositories/file_repository.py
pytestee/domain/__init__.py
pytestee/domain/interfaces.py
pytestee/domain/models.py
pytestee/domain/analyzers/__init__.py
pytestee/domain/analyzers/assertion_analyzer.py
pytestee/domain/analyzers/pattern_analyzer.py
pytestee/domain/rules/__init__.py
pytestee/domain/rules/base_rule.py
pytestee/domain/rules/rule_validator.py
pytestee/domain/rules/assertion/__init__.py
pytestee/domain/rules/assertion/assertion_count_ok.py
pytestee/domain/rules/assertion/high_assertion_density.py
pytestee/domain/rules/assertion/no_assertions.py
pytestee/domain/rules/assertion/too_few_assertions.py
pytestee/domain/rules/assertion/too_many_assertions.py
pytestee/domain/rules/comment/__init__.py
pytestee/domain/rules/comment/aaa_comment_pattern.py
pytestee/domain/rules/comment/aaa_or_gwt_pattern.py
pytestee/domain/rules/comment/gwt_comment_pattern.py
pytestee/domain/rules/logic/__init__.py
pytestee/domain/rules/logic/logical_flow_pattern.py
pytestee/domain/rules/naming/__init__.py
pytestee/domain/rules/naming/japanese_characters.py
pytestee/domain/rules/naming/japanese_class_names.py
pytestee/domain/rules/naming/test_class_method_count.py
pytestee-0.1.0.dist-info/METADATA
pytestee-0.1.0.dist-info/WHEEL
pytestee-0.1.0.dist-info/entry_points.txt
pytestee-0.1.0.dist-info/licenses/LICENSE
pytestee-0.1.0.dist-info/RECORD
