Metadata-Version: 2.4
Name: pytestee
Version: 0.1.0
Summary: pytest test quality checker CLI tool
Project-URL: Homepage, https://github.com/mmocchi/pytestee
Project-URL: Documentation, https://github.com/mmocchi/pytestee
Project-URL: Repository, https://github.com/mmocchi/pytestee
Project-URL: Issues, https://github.com/mmocchi/pytestee/issues
Author-email: mmocchi <mmocchi@example.com>
License: MIT License
License-File: LICENSE
Keywords: cli,pytest,quality,testing
Classifier: Development Status :: 3 - Alpha
Classifier: Intended Audience :: Developers
Classifier: License :: OSI Approved :: MIT License
Classifier: Programming Language :: Python :: 3
Classifier: Programming Language :: Python :: 3.9
Classifier: Programming Language :: Python :: 3.10
Classifier: Programming Language :: Python :: 3.11
Classifier: Programming Language :: Python :: 3.12
Classifier: Topic :: Software Development :: Quality Assurance
Classifier: Topic :: Software Development :: Testing
Requires-Python: >=3.9
Requires-Dist: click>=8.0.0
Requires-Dist: colorama>=0.4.6
Requires-Dist: rich>=13.0.0
Requires-Dist: tomli>=1.2.0; python_version < '3.11'
Provides-Extra: dev
Requires-Dist: mypy>=1.0.0; extra == 'dev'
Requires-Dist: pytest-cov>=4.0.0; extra == 'dev'
Requires-Dist: pytest>=7.0.0; extra == 'dev'
Requires-Dist: ruff>=0.1.0; extra == 'dev'
Requires-Dist: types-colorama; extra == 'dev'
